tessellate/__init__.py
tessellate/cli.py
tessellate/tessellate.py
tessellate/utils/__init__.py
tessellate/utils/getRing.py
tessellate/utils/helperfunctions.py
tessellate/utils/pucker.py
tessellate-0.3.7.dist-info/DESCRIPTION.rst
tessellate-0.3.7.dist-info/METADATA
tessellate-0.3.7.dist-info/RECORD
tessellate-0.3.7.dist-info/WHEEL
tessellate-0.3.7.dist-info/entry_points.txt
tessellate-0.3.7.dist-info/metadata.json
tessellate-0.3.7.dist-info/top_level.txt
tests/__init__.py
tests/test_tessellate.py
