Metadata-Version: 2.0
Name: tessellate
Version: 0.3.7
Summary: A package for quantifying cyclic molecule conformations.
Home-page: https://github.com/chrisbarnettster/tessellate
Author: Christopher Bevan Barnett
Author-email: chrisbarnettster@gmail.com
License: Apache Software License 2.0
Keywords: tessellate
Platform: UNKNOWN
Classifier: Development Status :: 2 - Pre-Alpha
Classifier: Intended Audience :: Developers
Classifier: License :: OSI Approved :: Apache Software License
Classifier: Natural Language :: English
Classifier: Programming Language :: Python :: 3
Classifier: Programming Language :: Python :: 3.3
Classifier: Programming Language :: Python :: 3.4
Classifier: Programming Language :: Python :: 3.5
Requires-Python: >=3
Requires-Dist: Click (>=6.0)
Requires-Dist: numpy
Requires-Dist: bson
Requires-Dist: biopython (>=1.70)
Requires-Dist: pandas
Requires-Dist: pytest
